regula/__init__.py
regula/documentreader/__init__.py
regula/documentreader/webclient/__init__.py
regula/documentreader/webclient/ext/__init__.py
regula/documentreader/webclient/ext/api/__init__.py
regula/documentreader/webclient/ext/api/document_reader_api.py
regula/documentreader/webclient/ext/models/__init__.py
regula/documentreader/webclient/ext/models/images.py
regula/documentreader/webclient/ext/models/raw_authenticity_result_item.py
regula/documentreader/webclient/ext/models/raw_result_item.py
regula/documentreader/webclient/ext/models/recognition_request.py
regula/documentreader/webclient/ext/models/recognition_response.py
regula/documentreader/webclient/ext/models/text.py
regula/documentreader/webclient/ext/models/text_field.py
regula/documentreader/webclient/ext/models/authenticity/__init__.py
regula/documentreader/webclient/ext/models/authenticity/authenticity_check_list.py
regula/documentreader/webclient/ext/models/authenticity/fiber.py
regula/documentreader/webclient/ext/models/authenticity/ident.py
regula/documentreader/webclient/ext/models/authenticity/image_ident.py
regula/documentreader/webclient/ext/models/authenticity/ocr_security_text.py
regula/documentreader/webclient/ext/models/authenticity/security_feature.py
regula/documentreader/webclient/gen/__init__.py
regula/documentreader/webclient/gen/api_client.py
regula/documentreader/webclient/gen/configuration.py
regula/documentreader/webclient/gen/exceptions.py
regula/documentreader/webclient/gen/rest.py
regula/documentreader/webclient/gen/api/__init__.py
regula/documentreader/webclient/gen/api/default_api.py
regula/documentreader/webclient/gen/api/process_api.py
regula/documentreader/webclient/gen/models/__init__.py
regula/documentreader/webclient/gen/models/area_array.py
regula/documentreader/webclient/gen/models/area_container.py
regula/documentreader/webclient/gen/models/authenticity_check_list.py
regula/documentreader/webclient/gen/models/authenticity_check_result.py
regula.documentreader.webclient-11.4.17.dist-info/METADATA
regula.documentreader.webclient-11.4.17.dist-info/WHEEL
regula.documentreader.webclient-11.4.17.dist-info/top_level.txt
regula.documentreader.webclient-11.4.17.dist-info/RECORD
