Metadata-Version: 2.1
Name: regula.documentreader.webclient
Version: 11.4.17
Summary: Regula's Document Reader python client
Home-page: https://mobile.regulaforensics.com
Author: Regula Forensics, Inc.
Author-email: support@regulaforensics.com
Keywords: document-reader-client,document reader,document recognition,regulaforensics,regula
Requires-Python: >=3.5
Requires-Dist: certifi ==2023.7.22
Requires-Dist: python-dateutil ==2.8.1
Requires-Dist: six ==1.15.0
Requires-Dist: urllib3 ==1.26.5
